odoo/addons/auth_oauth_autologin/README.rst
odoo/addons/auth_oauth_autologin/__init__.py
odoo/addons/auth_oauth_autologin/__manifest__.py
odoo/addons/auth_oauth_autologin/controllers/__init__.py
odoo/addons/auth_oauth_autologin/controllers/main.py
odoo/addons/auth_oauth_autologin/i18n/auth_oauth_autologin.pot
odoo/addons/auth_oauth_autologin/models/__init__.py
odoo/addons/auth_oauth_autologin/models/auth_oauth_provider.py
odoo/addons/auth_oauth_autologin/readme/CONFIGURE.rst
odoo/addons/auth_oauth_autologin/readme/DESCRIPTION.rst
odoo/addons/auth_oauth_autologin/readme/USAGE.rst
odoo/addons/auth_oauth_autologin/static/description/icon.png
odoo/addons/auth_oauth_autologin/static/description/index.html
odoo/addons/auth_oauth_autologin/tests/__init__.py
odoo/addons/auth_oauth_autologin/tests/test_auth_oauth_autologin.py
odoo/addons/auth_oauth_autologin/views/auth_oauth_provider.xml
odoo14_addon_auth_oauth_autologin-14.0.1.0.1.dist-info/METADATA
odoo14_addon_auth_oauth_autologin-14.0.1.0.1.dist-info/WHEEL
odoo14_addon_auth_oauth_autologin-14.0.1.0.1.dist-info/top_level.txt
odoo14_addon_auth_oauth_autologin-14.0.1.0.1.dist-info/RECORD
